cefrpy/CEFRAnalyzer.py
cefrpy/CEFRDataProcessor.py
cefrpy/CEFRDataReader.py
cefrpy/CEFRDataValidator.py
cefrpy/CEFRLevel.py
cefrpy/CEFRSpaCyAnalyzer.py
cefrpy/POSTag.py
cefrpy/__init__.py
cefrpy/data.bin
cefrpy-1.0.1.dist-info/LICENSE
cefrpy-1.0.1.dist-info/METADATA
cefrpy-1.0.1.dist-info/WHEEL
cefrpy-1.0.1.dist-info/top_level.txt
cefrpy-1.0.1.dist-info/RECORD
