Metadata-Version: 2.1
Name: cefrpy
Version: 1.0.1
Summary: Python package for analyzing words based on the CEFR level.
Author: Maxim Belikov
Author-email: maximax6767@gmail.com
Classifier: Programming Language :: Python :: 3
Classifier: License :: OSI Approved :: MIT License
Classifier: Operating System :: OS Independent
Requires-Python: >=3.6
License-File: LICENSE
